korean_rps/__init__.py
korean_rps/game.py
korean_rps-1.0.1.dist-info/METADATA
korean_rps-1.0.1.dist-info/WHEEL
korean_rps-1.0.1.dist-info/top_level.txt
korean_rps-1.0.1.dist-info/RECORD
