Metadata-Version: 2.1
Name: korean-rps
Version: 1.0.1
Summary: 가위바위보 라이브러리
Home-page: UNKNOWN
Author: VoidAsMad
Author-email: voidasmad@gmail.com
License: MIT
Platform: UNKNOWN
Requires-Python: >=3.6
